{
  "variants": {
    "facing=north":
    {
      "model": "habitat:block/fairy_ring_mushroom_vertical_slab",
      "y": 0,
      "uvlock": true
    },
    "facing=south":
    {
      "model": "habitat:block/fairy_ring_mushroom_vertical_slab",
      "y": 180,
      "uvlock": true
    },
    "facing=east":
    {
      "model": "habitat:block/fairy_ring_mushroom_vertical_slab",
      "y": 90,
      "uvlock": true
    },
    "facing=west":
    {
      "model": "habitat:block/fairy_ring_mushroom_vertical_slab",
      "y": 270,
      "uvlock": true
    },
    "type=double":
    {
      "model": "habitat:block/fairy_ring_mushroom_planks"
    }
  }
}